{"assignedPosition":"Middle","cellId":0,"championId":268,"championPickIntent":0,"entitledFeatureType":"","selectedSkinId":268000,"spell1Id":0,"spell2Id":0,"summonerId":0,"team":1,"wardSkinId":-1,"counters":[{"counter":"Corki","win":"65.67%","played":"67"},{"counter":"Heimerdinger","win":"58.33%","played":"48"},{"counter":"Twisted Fate","win":"57.14%","played":"63"},{"counter":"Jayce","win":"56.67%","played":"30"},{"counter":"Syndra","win":"55.13%","played":"78"},{"counter":"Gangplank","win":"55.10%","played":"49"},{"counter":"Anivia","win":"54.07%","played":"135"},{"counter":"Tristana","win":"53.23%","played":"62"},{"counter":"Talon","win":"52.44%","played":"82"},{"counter":"Annie","win":"52.00%","played":"75"},{"counter":"Cassiopeia","win":"51.65%","played":"91"},{"counter":"Yone","win":"51.15%","played":"260"},{"counter":"Seraphine","win":"50.91%","played":"55"},{"counter":"Rumble","win":"50.62%","played":"81"},{"counter":"Xerath","win":"50.38%","played":"133"},{"counter":"Ryze","win":"50.00%","played":"38"},{"counter":"Zed","win":"49.64%","played":"278"},{"counter":"Taliyah","win":"49.21%","played":"126"},{"counter":"Zilean","win":"48.84%","played":"43"},{"counter":"Lissandra","win":"48.19%","played":"83"},{"counter":"Vladimir","win":"48.12%","played":"266"},{"counter":"LeBlanc","win":"47.95%","played":"146"},{"counter":"Vel'Koz","win":"47.46%","played":"59"},{"counter":"Sylas","win":"47.43%","played":"487"},{"counter":"Veigar","win":"47.22%","played":"144"},{"counter":"Fizz","win":"46.81%","played":"94"},{"counter":"Vex","win":"46.43%","played":"196"},{"counter":"Ahri","win":"46.39%","played":"360"},{"counter":"Akshan","win":"45.98%","played":"87"},{"counter":"Kassadin","win":"45.74%","played":"129"},{"counter":"Kayle","win":"45.71%","played":"35"},{"counter":"Swain","win":"45.63%","played":"160"},{"counter":"Viktor","win":"45.28%","played":"519"},{"counter":"Katarina","win":"45.22%","played":"230"},{"counter":"Gragas","win":"45.00%","played":"40"},{"counter":"Malzahar","win":"44.64%","played":"112"},{"counter":"Yasuo","win":"44.40%","played":"232"},{"counter":"Orianna","win":"42.86%","played":"84"},{"counter":"Akali","win":"42.73%","played":"220"},{"counter":"Zoe","win":"42.70%","played":"178"},{"counter":"Irelia","win":"42.34%","played":"111"},{"counter":"Brand","win":"41.94%","played":"31"},{"counter":"Ekko","win":"41.74%","played":"115"},{"counter":"Ziggs","win":"40.68%","played":"59"},{"counter":"Lux","win":"40.40%","played":"151"},{"counter":"Pantheon","win":"40.00%","played":"35"},{"counter":"Diana","win":"38.71%","played":"62"},{"counter":"Neeko","win":"38.24%","played":"34"},{"counter":"Qiyana","win":"37.62%","played":"101"},{"counter":"Galio","win":"35.16%","played":"91"}],"possiblePositions":["Middle"]}