[{"counter":"Darius","win":"296","played":"220"},{"counter":"Jax","win":"227","played":"206"},{"counter":"Mordekaiser","win":"220","played":"205"},{"counter":"Garen","win":"212","played":"194"},{"counter":"Wukong","win":"206","played":"171"},{"counter":"Irelia","win":"205","played":"136"},{"counter":"Shen","win":"205","played":"135"},{"counter":"Sion","win":"202","played":"114"},{"counter":"Renekton","win":"194","played":"105"},{"counter":"Yone","win":"185","played":"100"},{"counter":"Urgot","win":"171","played":"96"},{"counter":"Volibear","win":"146","played":"84"},{"counter":"Tryndamere","win":"136","played":"77"},{"counter":"Graves","win":"135","played":"65"},{"counter":"Yorick","win":"135","played":"61"},{"counter":"Pantheon","win":"134","played":"59"},{"counter":"Singed","win":"114","played":"54"},{"counter":"Kennen","win":"111","played":"50"},{"counter":"Poppy","win":"105","played":"42"},{"counter":"Tahm Kench","win":"103","played":"40"},{"counter":"Swain","win":"100","played":"38"},{"counter":"Vayne","win":"97","played":"35"},{"counter":"Warwick","win":"96","played":"31"},{"counter":"Kled","win":"89","played":"30"},{"counter":"Quinn","win":"64.00%","played":"39"},{"counter":"Illaoi","win":"58.52%","played":"64"},{"counter":"Yasuo","win":"56.25%","played":"33"},{"counter":"Gnar","win":"55.26%","played":"55"},{"counter":"Ornn","win":"53.96%","played":"134"},{"counter":"Cho'Gath","win":"53.73%","played":"59"},{"counter":"","win":"53.72%","played":"227"},{"counter":"Nasus","win":"53.42%","played":"89"},{"counter":"Sett","win":"52.83%","played":"202"},{"counter":"Gragas","win":"52.58%","played":"36"},{"counter":"Vladimir","win":"51.35%","played":"52"},{"counter":"Riven","win":"50.97%","played":"185"},{"counter":"Kayle","win":"50.24%","played":"146"},{"counter":"Dr. Mundo","win":"49.51%","played":"42"},{"counter":"Malphite","win":"48.78%","played":"135"},{"counter":"Gangplank","win":"48.64%","played":"205"},{"counter":"Gwen","win":"48.54%","played":"97"},{"counter":"Akshan","win":"47.62%","played":"48"},{"counter":"Akali","win":"47.06%","played":"78"},{"counter":"Jayce","win":"46.49%","played":"103"},{"counter":"Rumble","win":"46.07%","played":"31"},{"counter":"Olaf","win":"45.88%","played":"111"},{"counter":"Rengar","win":"44.05%"},{"counter":"Teemo","win":"43.70%","played":"68"},{"counter":"Camille","win":"41.85%","played":"212"}]